livvkit/__init__.py
livvkit/__main__.py
livvkit/scheduler.py
livvkit/bundles/__init__.py
livvkit/bundles/CISM_glissade/__init__.py
livvkit/bundles/CISM_glissade/numerics.json
livvkit/bundles/CISM_glissade/numerics.py
livvkit/bundles/CISM_glissade/performance.json
livvkit/bundles/CISM_glissade/verification.json
livvkit/bundles/CISM_glissade/verification.py
livvkit/components/__init__.py
livvkit/components/numerics.py
livvkit/components/performance.py
livvkit/components/validation.py
livvkit/components/verification.py
livvkit/components/numerics_tests/__init__.py
livvkit/components/numerics_tests/ismip.json
livvkit/components/numerics_tests/ismip.py
livvkit/data/Evans2019.bib
livvkit/data/Kennedy2017.bib
livvkit/data/__init__.py
livvkit/data/numerics/__init__.py
livvkit/data/numerics/ismip-hom/ExpA_Fig5_005.txt
livvkit/data/numerics/ismip-hom/ExpA_Fig5_010.txt
livvkit/data/numerics/ismip-hom/ExpA_Fig5_020.txt
livvkit/data/numerics/ismip-hom/ExpA_Fig5_040.txt
livvkit/data/numerics/ismip-hom/ExpA_Fig5_080.txt
livvkit/data/numerics/ismip-hom/ExpA_Fig5_160.txt
livvkit/data/numerics/ismip-hom/ExpC_Fig8_005.txt
livvkit/data/numerics/ismip-hom/ExpC_Fig8_010.txt
livvkit/data/numerics/ismip-hom/ExpC_Fig8_020.txt
livvkit/data/numerics/ismip-hom/ExpC_Fig8_040.txt
livvkit/data/numerics/ismip-hom/ExpC_Fig8_080.txt
livvkit/data/numerics/ismip-hom/ExpC_Fig8_160.txt
livvkit/data/numerics/ismip-hom/ExpF_Fig12_000.txt
livvkit/data/numerics/ismip-hom/ExpF_Fig12_001.txt
livvkit/data/numerics/ismip-hom/ExpF_Fig13_000.txt
livvkit/data/numerics/ismip-hom/ExpF_Fig13_001.txt
livvkit/elements/__init__.py
livvkit/elements/elements.py
livvkit/elements/templates/bit4bit.html
livvkit/elements/templates/bit4bit.tex
livvkit/elements/templates/diff.html
livvkit/elements/templates/diff.tex
livvkit/elements/templates/document.tex
livvkit/elements/templates/err.html
livvkit/elements/templates/err.tex
livvkit/elements/templates/gallery.html
livvkit/elements/templates/gallery.tex
livvkit-3.2.0.dist-info/licenses/LICENSE
livvkit-3.2.0.dist-info/METADATA
livvkit-3.2.0.dist-info/WHEEL
livvkit-3.2.0.dist-info/entry_points.txt
livvkit-3.2.0.dist-info/top_level.txt
livvkit-3.2.0.dist-info/RECORD
