Metadata-Version: 2.4
Name: livvkit
Version: 3.2.0
Summary: The land ice verification and validation toolkit
Author-email: Michael Kelleher <kelleherme@ornl.gov>, "Joseph H. Kennedy" <kennedyjh@ornl.gov>
License: BSD-3-Clause
Project-URL: Homepage, https://github.com/LIVVkit/LIVVkit
Classifier: Development Status :: 5 - Production/Stable
Classifier: Intended Audience :: Science/Research
Classifier: Topic :: Scientific/Engineering
Classifier: Topic :: Software Development :: Testing
Classifier: License :: OSI Approved :: BSD License
Classifier: Natural Language :: English
Classifier: Operating System :: OS Independent
Classifier: Programming Language :: Python :: 3
Classifier: Programming Language :: Python :: 3.9
Classifier: Programming Language :: Python :: 3.10
Classifier: Programming Language :: Python :: 3.11
Classifier: Programming Language :: Python :: 3.12
Classifier: Programming Language :: Python :: 3.13
Requires-Python: >=3.9
License-File: LICENSE
Requires-Dist: setuptools
Requires-Dist: pip
Requires-Dist: numpy
Requires-Dist: scipy
Requires-Dist: netcdf4
Requires-Dist: matplotlib
Requires-Dist: jinja2
Requires-Dist: json_tricks>=3.11.0
Requires-Dist: pybtex
Requires-Dist: pandas>=2.1.0
Requires-Dist: nodejs
Requires-Dist: ruamel.yaml
Provides-Extra: dev
Requires-Dist: ruff; extra == "dev"
Requires-Dist: isort; extra == "dev"
Requires-Dist: pytest; extra == "dev"
Requires-Dist: pytest-cov; extra == "dev"
Requires-Dist: tox; extra == "dev"
Requires-Dist: requests; extra == "dev"
Requires-Dist: sphinx; extra == "dev"
Requires-Dist: sphinx-js; extra == "dev"
Requires-Dist: sphinx-py3doc-enhanced-theme; extra == "dev"
Dynamic: license-file
